threads/__init__.py
threads/__version__.py
threads/api.py
threads_sdk-0.2.2.dist-info/LICENSE
threads_sdk-0.2.2.dist-info/METADATA
threads_sdk-0.2.2.dist-info/WHEEL
threads_sdk-0.2.2.dist-info/top_level.txt
threads_sdk-0.2.2.dist-info/RECORD
